<?xml version='1.0' encoding='ISO-8859-1'?>
<FChoiceList>
<choice>
  <name>Bilateral</name>
</choice>
<choice>
  <name>LCH.Clearnet</name>
</choice>
<choice>
  <name>CME</name>
</choice>
<choice>
  <name>AmendOrCancelDirectDeal</name>
</choice>
<choice>
  <name>DirectDeal</name>
</choice>
<choice>
  <name>DirectDealNovationStepOut</name>
</choice>
<choice>
  <name>DirectDealNovationRemaining</name>
</choice>
<choice>
  <name>LCH_Clearnet_T2_CB</name>
</choice>
<choice>
  <name>LCH_Clearnet_T2_Client</name>
</choice>
<choice>
  <name>LCH_Clearnet_T2_EB</name>
</choice>
<choice>
  <name>T2_CB</name>
</choice>
<choice>
  <name>T2_Client</name>
</choice>
<choice>
  <name>T2_EB</name>
</choice>
</FChoiceList>
