<?xml version='1.0' encoding='ISO-8859-1'?>
<FChoiceList>
<description>Domestic Money Market Instype</description>
<choice>
  <name>BA</name>
  <description>Bankers Acceptance</description>
</choice>
<choice>
  <name>TB</name>
  <description>Treasury Bill</description>
</choice>
<choice>
  <name>LBB</name>
  <description>Landbank Bill</description>
</choice>
<choice>
  <name>PN</name>
  <description>Promissory Note</description>
</choice>
<choice>
  <name>NCD</name>
  <description>Negiotable Credit Derivative</description>
</choice>
<choice>
  <name>Comm Paper</name>
  <description>Commercial Paper</description>
</choice>
<choice>
  <name>SARB Debenture</name>
  <description>SARB Debenture</description>
</choice>
<choice>
  <name>PNCD</name>
  <description>Prime Linked NCD</description>
</choice>
<choice>
  <name>PRN</name>
  <description>PN Issued</description>
</choice>
<choice>
  <name>PRP</name>
  <description>PN Purchased</description>
</choice>
<choice>
  <name>PNS</name>
</choice>
<choice>
  <name>DBE</name>
</choice>
<choice>
  <name>CD</name>
  <description>Structured Deposit</description>
</choice>
<choice>
  <name>CL</name>
  <description>Structured Loan</description>
</choice>
<choice>
  <name>NCF</name>
  <description>FLoating Negotiable Struct</description>
</choice>
<choice>
  <name>FRN</name>
  <description>Floating Rate Note</description>
</choice>
<choice>
  <name>SNR</name>
  <description>Senior Paper</description>
</choice>
<choice>
  <order>1</order>
  <name>IPS</name>
  <description>IPS</description>
</choice>
<choice>
  <order>1</order>
  <name>IRS</name>
  <description>IRS</description>
</choice>
<choice>
  <order>1</order>
  <name>NCC</name>
  <description>NCC</description>
</choice>
<choice>
  <order>1</order>
  <name>FDI</name>
  <description>FDI</description>
</choice>
<choice>
  <name>FLI</name>
  <description>Float Loan</description>
</choice>
<choice>
  <name>CLmtm</name>
  <description>CLmtm</description>
</choice>
<choice>
  <name>CDmtm</name>
  <description>CDmtm</description>
</choice>
<choice>
  <name>Ext Note Listed</name>
  <description>Extendable Note Listed</description>
</choice>
<choice>
  <name>Ext Note Unlisted</name>
  <description>Extendable Note Unlisted</description>
</choice>
<choice>
  <name>CD SNR</name>
  <description>CD SNR Linked</description>
</choice>
<choice>
  <name>CL SNR</name>
  <description>CL SNR Linked</description>
</choice>
<choice>
  <name>CLN</name>
  <description>CLN</description>
</choice>
<choice>
  <name>LEV CLN</name>
  <description>Leveraged CLN</description>
</choice>
<choice>
  <name>CL Non Zar</name>
  <description>CL Non Zar</description>
</choice>
<choice>
  <name>CD Non Zar</name>
  <description>CD Non Zar</description>
</choice>
<choice>
  <name>CL Pre Payable</name>
  <description>CL Pre Payable</description>
</choice>
<choice>
  <name>CD Pre Payable</name>
  <description>CD Pre Payable</description>
</choice>
<choice>
  <name>FRD Pre Payable</name>
  <description>FRD Pre Payable</description>
</choice>
<choice>
  <name>FRD Pre Payable 3M</name>
  <description>FRD Pre Payable 3M</description>
</choice>
<choice>
  <name>FRD Pre Payable 1M</name>
  <description>FRD Pre Payable 1M</description>
</choice>
<choice>
  <name>FRD Pre Payable 6M</name>
  <description>FRD Pre Payable 6M</description>
</choice>
<choice>
  <name>Corp Bonds Floating</name>
  <description>Corp Bonds Floating</description>
</choice>
<choice />
<choice>
  <name>FRD Pre Payable 13M</name>
  <description>FRD Pre Payable 13M</description>
</choice>
<choice>
  <name>SS</name>
  <description>Structured Swap</description>
</choice>
<choice>
  <name>LNCD</name>
  <description>Linked Negotiable Certificate of Dep</description>
</choice>
</FChoiceList>
